{
  "dishes": [
    {
      "id": 0,
      "name": "Ratatouille",
      "image": "images/Ratatouille.jpg",
      "category": "mains",
      "label": "Hot",
      "price": "4.99",
      "featured": true,
      "description": "Ratatouille is a French Provençal stewed vegetable dish, originating in Nice, and sometimes referred to as ratatouille niçoise. Layers of spiced tomato sauce, creamy béchamel, and layers of veggies - yellow squash, zucchini, eggplant, potato, bell pepper. What else do you need?"
    },
    {
      "id": 1,
      "name": "Croissants",
      "image": "images/Croissants.jpg",
      "category": "Bakery",
      "label": "",
      "price": "1.99",
      "featured": false,
      "description": "A croissant is a buttery, flaky, viennoiserie pastry.Croissants are made of a layered yeast-leavened dough. The dough is layered with butter, rolled and folded several times in succession, then rolled into a thin sheet, in a technique called laminating. The process results in a layered, flaky texture, similar to a puff pastry."
    },
    {
      "id": 2,
      "name": "Macaron",
      "image": "images/macaron.jpg",
      "category": "Confectionery",
      "label": "New",
      "price": "1.99",
      "featured": false,
      "description": "A macaron is a sweet meringue-based confection made with egg white, icing sugar, granulated sugar and almond meal."
    },
    {
      "id": 3,
      "name": "Soufflé",
      "image": "images/Soufflé.jpeg",
      "category": "dessert",
      "label": "",
      "price": "2.99",
      "featured": false,
      "description": "A soufflé is a baked egg-based dish originating in France in the early eighteenth century. Combined with various other ingredients it can be served as a savory main dish or sweetened as a dessert. "
    }
  ],
  "comments": [
    {
      "id": 0,
      "dishId": 0,
      "rating": 5,
      "comment": "Lovely Food",
      "author": "Aniket",
      "date": "2020-12-16T17:57:28.556094Z"
    },
    {
      "id": 1,
      "dishId": 0,
      "rating": 4,
      "comment": "This is a test comment",
      "author": "Aniket",
      "date": "2020-12-05T17:57:28.556094Z"
    },
    {
      "id": 2,
      "dishId": 0,
      "rating": 3,
      "comment": "Eat it, just eat it!",
      "author": "Aniket",
      "date": "2015-12-13T17:57:28.556094Z"
    },
    {
      "id": 3,
      "dishId": 0,
      "rating": 4,
      "comment": "This is a test comment",
      "author": "Aniket",
      "date": "2020-12-02T17:57:28.556094Z"
    },
    {
      "id": 4,
      "dishId": 0,
      "rating": 2,
      "comment": "This is a test comment",
      "author": "Aniket",
      "date": "2020-12-02T17:57:28.556094Z"
    },
    {
      "id": 5,
      "dishId": 1,
      "rating": 5,
      "comment": "This is a test comment!",
      "author": "Aniket",
      "date": "2020-10-16T17:57:28.556094Z"
    },
    {
      "id": 6,
      "dishId": 1,
      "rating": 4,
      "comment": "This is a test comment!",
      "author": "Aniket",
      "date": "2020-09-05T17:57:28.556094Z"
    },
    {
      "id": 7,
      "dishId": 1,
      "rating": 3,
      "comment": "This is a test comment!",
      "author": "Aniket",
      "date": "2020-02-13T17:57:28.556094Z"
    },
    {
      "id": 8,
      "dishId": 1,
      "rating": 4,
      "comment": "This is a test comment!",
      "author": "Aniket",
      "date": "2020-12-02T17:57:28.556094Z"
    },
    {
      "id": 9,
      "dishId": 1,
      "rating": 2,
      "comment": "This is a test comment!",
      "author": "Aniket",
      "date": "2020-12-02T17:57:28.556094Z"
    },
    {
      "id": 10,
      "dishId": 2,
      "rating": 5,
      "comment": "This is a test comment!",
      "author": "Aniket",
      "date": "2012-10-16T17:57:28.556094Z"
    },
    {
      "id": 11,
      "dishId": 2,
      "rating": 4,
      "comment": "This is a test comment!",
      "author": "Aniket",
      "date": "2020-09-05T17:57:28.556094Z"
    },
    {
      "id": 12,
      "dishId": 2,
      "rating": 3,
      "comment": "This is a test comment!",
      "author": "Aniket",
      "date": "2015-02-13T17:57:28.556094Z"
    },
    {
      "id": 13,
      "dishId": 2,
      "rating": 4,
      "comment": "This is a test comment!",
      "author": "Aniket",
      "date": "2020-12-02T17:57:28.556094Z"
    },
    {
      "id": 14,
      "dishId": 2,
      "rating": 2,
      "comment": "This is a test comment!",
      "author": "Aniket",
      "date": "2020-12-02T17:57:28.556094Z"
    },
    {
      "id": 15,
      "dishId": 3,
      "rating": 5,
      "comment": "This is a test comment!",
      "author": "Aniket",
      "date": "2020-10-16T17:57:28.556094Z"
    },
    {
      "id": 16,
      "dishId": 3,
      "rating": 4,
      "comment": "This is a test comment!",
      "author": "Aniket",
      "date": "2020-09-05T17:57:28.556094Z"
    },
    {
      "id": 17,
      "dishId": 3,
      "rating": 3,
      "comment": "This is a test comment!",
      "author": "Aniket",
      "date": "2020-02-13T17:57:28.556094Z"
    },
    {
      "id": 18,
      "dishId": 3,
      "rating": 4,
      "comment": "This is a test comment!",
      "author": "Aniket",
      "date": "2020-12-02T17:57:28.556094Z"
    },
    {
      "id": 19,
      "dishId": 3,
      "rating": 2,
      "comment": "This is a test comment!",
      "author": "Aniket",
      "date": "2020-12-02T17:57:28.556094Z"
    },
    {
      "dishId": 3,
      "rating": "5",
      "author": "Aniket ",
      "comment": "This is a test comment",
      "date": "2020-06-18T18:46:51.517Z",
      "id": 20
    }
  ],
  "promotions": [
    {
      "id": 0,
      "name": "Weekend Grand Buffet",
      "image": "images/Buffet.jpeg",
      "label": "New",
      "price": "19.99",
      "featured": true,
      "description": "Featuring mouthwatering combinations with a choice of five different salads, six enticing appetizers, six main entrees and five choicest desserts. All for just $19.99 per person "
    }
  ],
  "leaders": [
    {
      "id": 0,
      "name": "Remy",
      "image": "images/Remy.jpg",
      "designation": "Chief Food Officer",
      "abbr": "CFO",
      "featured": false,
      "description": "Don't go by his size. Remy is a perfectionist when it comes to cooking. Even the best food critics are fans of his dishes. He is popularly known as the 'Little Chef'."
    },
    {
      "id": 1,
      "name": "Anton Ego",
      "image": "images/Anton.jpg",
      "designation": "Chief Taste Officer",
      "abbr": "CTO",
      "featured": false,
      "description": "Blessed with the most discerning gustatory sense, Anton, our CTO, personally ensures that every dish that we serve meets his exacting tastes. Our chefs dread the tongue lashing that ensues if their dish does not meet his exacting standards."
    },
    {
      "id": 2,
      "name": "Alfredo Linguini",
      "image": "images/Alfredo.jpg",
      "designation": "Executive Chef",
      "abbr": "EC",
      "featured": true,
      "description": "Award winning three-star Michelin chef with wide International experience having worked closely with whos-who in the culinary world, he specializes in creating mouthwatering Ratatouille."
    }
  ],
  "feedback": [
    {
      "firstname": "fdas",
      "lastname": "afds",
      "telnum": "134113",
      "email": "dafdads@daffas.dfdafd",
      "agree": true,
      "contactType": "Email",
      "message": "afadsfds",
      "date": "2017-12-04T09:41:49.890Z",
      "id": 1
    }
  ]
}